wrap_rocks-0.6.3.dist-info/METADATA
wrap_rocks-0.6.3.dist-info/WHEEL
wrap_rocks-0.6.3.dist-info/licenses/LICENSE
wrap_rocks/__init__.py
wrap_rocks/wrap_rocks.cpython-311-x86_64-linux-gnu.so
wrap_rocks-0.6.3.dist-info/RECORD
