Metadata-Version: 2.4
Name: wrap_rocks
Version: 0.6.3
Classifier: Development Status :: 4 - Beta
Classifier: Intended Audience :: Developers
Classifier: Programming Language :: Rust
Classifier: Programming Language :: Python :: 3.8
Classifier: Programming Language :: Python :: 3.9
Classifier: Programming Language :: Python :: 3.10
Classifier: Programming Language :: Python :: 3.11
Classifier: Programming Language :: Python :: 3.12
Classifier: Programming Language :: Python :: 3.13
Classifier: Programming Language :: Python :: Implementation :: CPython
Classifier: Topic :: Database
Classifier: Topic :: Software Development :: Libraries
Classifier: Topic :: System :: Filesystems
License-File: LICENSE
Keywords: RocksDB,database,key-value store,Python wrapper,rocksdb,storage,embedded database,high-performance,database binding
Author: Michael Valentine
Author-email: mvalentine65@gmail.com
License: Apache-2.0
Requires-Python: >=3.8
